manage_sql/__init__.py
manage_sql/Utils/MYSQL.py
manage_sql/Utils/POSTGRESQL.py
manage_sql/Utils/SQLITE.py
manage_sql/Utils/__init__.py
manage_sql/Utils/utils_mysql.py
manage_sql/Utils/utils_postgres.py
manage_sql/Utils/utils_sqlite.py
manage_sql-1.0.8.dist-info/licenses/LICENCE
manage_sql-1.0.8.dist-info/METADATA
manage_sql-1.0.8.dist-info/WHEEL
manage_sql-1.0.8.dist-info/top_level.txt
manage_sql-1.0.8.dist-info/RECORD
