Metadata-Version: 2.4
Name: manage-sql
Version: 1.0.8
Summary: Python library for managing SQLite, MySQL, and PostgreSQL databases with greater efficiency.
Author-email: Web Tech Moz <zoidycine@gmail.com>
License: MIT
Keywords: manage-sql,sqlite,sqlite manager,mysql,mysql manager,mysql python,mysql connector,postgresql connector,postgresql,postgresql python
Classifier: Programming Language :: Python :: 3.12
Classifier: Programming Language :: Python :: 3.11
Classifier: Programming Language :: Python :: 3.10
Classifier: Programming Language :: Python :: 3.7
Classifier: Programming Language :: Python :: 3.6
Classifier: License :: OSI Approved :: MIT License
Classifier: Operating System :: OS Independent
Requires-Python: >=3.6
License-File: LICENCE
Requires-Dist: mysql-connector
Requires-Dist: mysql-connector-python
Requires-Dist: psycopg2-binary
Dynamic: license-file
